mat3ra/__init__.py
mat3ra/made/__init__.py
mat3ra/made/cell.py
mat3ra/made/lattice.py
mat3ra/made/material.py
mat3ra/made/metadata.py
mat3ra/made/utils.py
mat3ra/made/basis/__init__.py
mat3ra/made/basis/coordinates.py
mat3ra/made/tools/README.md
mat3ra/made/tools/__init__.py
mat3ra/made/tools/helpers.py
mat3ra/made/tools/modify.py
mat3ra/made/tools/optimize.py
mat3ra/made/tools/third_party.py
mat3ra/made/tools/utils.py
mat3ra/made/tools/analyze/__init__.py
mat3ra/made/tools/analyze/build_metadata_analyzer.py
mat3ra/made/tools/analyze/coordination.py
mat3ra/made/tools/analyze/lattice_lines.py
mat3ra/made/tools/analyze/lattice_planes.py
mat3ra/made/tools/analyze/material.py
mat3ra/made/tools/analyze/other.py
mat3ra/made/tools/analyze/rdf.py
mat3ra/made/tools/analyze/slab.py
mat3ra/made/tools/analyze/terrace.py
mat3ra/made/tools/analyze/utils.py
mat3ra/made/tools/analyze/basis/__init__.py
mat3ra/made/tools/analyze/basis/analyzer.py
mat3ra/made/tools/analyze/basis/fingerprint.py
mat3ra/made/tools/analyze/crystal_site/__init__.py
mat3ra/made/tools/analyze/crystal_site/adatom_crystal_site_material_analyzer.py
mat3ra/made/tools/analyze/crystal_site/adatom_material_analyzer.py
mat3ra/made/tools/analyze/crystal_site/crystal_site_analyzer.py
mat3ra/made/tools/analyze/crystal_site/voronoi_crystal_site_analyzer.py
mat3ra/made/tools/analyze/interface/__init__.py
mat3ra/made/tools/analyze/interface/commensurate.py
mat3ra/made/tools/analyze/interface/enums.py
mat3ra/made/tools/analyze/interface/grain_boundary.py
mat3ra/made/tools/analyze/interface/simple.py
mat3ra/made/tools/analyze/interface/twisted_nanoribbons.py
mat3ra/made/tools/analyze/interface/zsl.py
mat3ra/made/tools/analyze/interface/utils/__init__.py
mat3ra/made/tools/analyze/interface/utils/holders.py
mat3ra/made/tools/analyze/interface/utils/vector.py
mat3ra/made/tools/analyze/lattice/__init__.py
mat3ra/made/tools/analyze/lattice/analyzer.py
mat3ra/made/tools/analyze/lattice/helpers.py
mat3ra_made-2025.11.13.post0.dist-info/licenses/LICENSE.md
mat3ra_made-2025.11.13.post0.dist-info/METADATA
mat3ra_made-2025.11.13.post0.dist-info/WHEEL
mat3ra_made-2025.11.13.post0.dist-info/entry_points.txt
mat3ra_made-2025.11.13.post0.dist-info/top_level.txt
mat3ra_made-2025.11.13.post0.dist-info/RECORD
