Metadata-Version: 2.4
Name: mat3ra-made
Version: 2025.11.13.post0
Summary: MAterials DEfinitions and/or MAterials DEsign library.
Author-email: "Exabyte Inc." <info@mat3ra.com>
License: # LICENSE
Classifier: Programming Language :: Python
Classifier: Programming Language :: Python :: 3
Classifier: Development Status :: 3 - Alpha
Classifier: Topic :: Software Development
Requires-Python: >=3.8
License-File: LICENSE.md
Requires-Dist: numpy<=1.26.4
Requires-Dist: mat3ra-utils
Requires-Dist: mat3ra-esse
Requires-Dist: mat3ra-code
Provides-Extra: tools
Requires-Dist: scipy; extra == "tools"
Requires-Dist: pymatgen==2024.4.13; extra == "tools"
Requires-Dist: ase; extra == "tools"
Requires-Dist: pymatgen-analysis-defects==2024.4.23; extra == "tools"
Provides-Extra: dev
Requires-Dist: pre-commit; extra == "dev"
Requires-Dist: black; extra == "dev"
Requires-Dist: ruff; extra == "dev"
Requires-Dist: isort; extra == "dev"
Requires-Dist: mypy; extra == "dev"
Requires-Dist: pip-tools; extra == "dev"
Provides-Extra: tests
Requires-Dist: coverage[toml]>=5.3; extra == "tests"
Requires-Dist: pytest; extra == "tests"
Requires-Dist: pytest-cov; extra == "tests"
Requires-Dist: gradio; extra == "tests"
Requires-Dist: pydantic; extra == "tests"
Requires-Dist: mat3ra-made[tools]; extra == "tests"
Requires-Dist: mat3ra-standata; extra == "tests"
Provides-Extra: all
Requires-Dist: mat3ra-made[tests]; extra == "all"
Requires-Dist: mat3ra-made[dev]; extra == "all"
Dynamic: license-file
